{
  "project_info": {
    "project_number": "626926301266",
    "project_id": "fir-notifications-projec-f2374",
    "storage_bucket": "fir-notifications-projec-f2374.appspot.com"
  },
  "client": [
    {
      "client_info": {
        "mobilesdk_app_id": "1:626926301266:android:8cc93f794eec94198def8b",
        "android_client_info": {
          "package_name": "com.example.flutter_fcm_notification"
        }
      },
      "oauth_client": [],
      "api_key": [
        {
          "current_key": "AIzaSyD7AlslcWLBbWZL7p3rG2RmgW1EydbMKds"
        }
      ],
      "services": {
        "appinvite_service": {
          "other_platform_oauth_client": []
        }
      }
    },
    {
      "client_info": {
        "mobilesdk_app_id": "1:626926301266:android:1b8b0e12bdf684af8def8b",
        "android_client_info": {
          "package_name": "com.example.flutter_firebase_notifications"
        }
      },
      "oauth_client": [],
      "api_key": [
        {
          "current_key": "AIzaSyD7AlslcWLBbWZL7p3rG2RmgW1EydbMKds"
        }
      ],
      "services": {
        "appinvite_service": {
          "other_platform_oauth_client": []
        }
      }
    }
  ],
  "configuration_version": "1"
}